MANIFEST.in
README.md
setup.py
4scanner.egg-info/PKG-INFO
4scanner.egg-info/SOURCES.txt
4scanner.egg-info/dependency_links.txt
4scanner.egg-info/requires.txt
4scanner.egg-info/top_level.txt
bin/4downloader
bin/4genconf
bin/4scanner
scanner/__init__.py
scanner/config.py
scanner/downloader.py
scanner/dupecheck.py
scanner/imageboard_info.py
scanner/thread_scanner.py
test/test.py