Metadata-Version: 1.1
Name: 4scanner
Version: 1.6.1
Summary: 4chan threads scanner
Home-page: https://github.com/Lacsap-/4scanner
Author: lacsap
Author-email: lacsap@cock.li
License: MIT
Keywords: 4chan scan download scrape scraper chan imageboard
Platform: UNKNOWN
Classifier: Development Status :: 4 - Beta
Classifier: Intended Audience :: End Users/Desktop
Classifier: License :: OSI Approved :: MIT License
Classifier: Programming Language :: Python :: 3
Classifier: Programming Language :: Python :: 3.3
Classifier: Programming Language :: Python :: 3.4
Classifier: Programming Language :: Python :: 3.5
